deploy/__init__.py
deploy/serverpc/__init__.py
deploy/serverpc/certification/__init__.py
deploy/serverpc/certification/certification_pipeline.py
tests/__init__.py
tests/test_audio_extraction.py
tests/test_dlc_pipeline.py
tests/test_ephys_compression_pipeline.py
tests/test_ephys_extraction_choiceWorld.py
tests/test_ephys_synchronization.py
tests/test_ephys_ttl_check.py
tests/test_training_extraction.py
tests/test_training_pipeline.py
tests/test_transfer_rig_data.py
tests/test_video_compression.py
iblscripts-0.0.1.dist-info/LICENSE
iblscripts-0.0.1.dist-info/METADATA
iblscripts-0.0.1.dist-info/WHEEL
iblscripts-0.0.1.dist-info/top_level.txt
iblscripts-0.0.1.dist-info/RECORD
